{
  "20260522": {
    "date": "20260522",
    "foreign": {
      "buy": 472332888344,
      "sell": 396196355691,
      "net": 76136532653
    },
    "trust": {
      "buy": 36509074727,
      "sell": 25283288167,
      "net": 11225786560
    },
    "dealer": {
      "buy": 53478833250,
      "sell": 34002507382,
      "net": 19476325868
    },
    "total_net": 106838645081
  },
  "20260521": {
    "date": "20260521",
    "foreign": {
      "buy": 398309751347,
      "sell": 337969068387,
      "net": 60340682960
    },
    "trust": {
      "buy": 32552166835,
      "sell": 27171867723,
      "net": 5380299112
    },
    "dealer": {
      "buy": 47293625214,
      "sell": 27697532182,
      "net": 19596093032
    },
    "total_net": 85317075104
  },
  "20260520": {
    "date": "20260520",
    "foreign": {
      "buy": 383226867202,
      "sell": 429847483184,
      "net": -46620615982
    },
    "trust": {
      "buy": 35288356651,
      "sell": 25079598064,
      "net": 10208758587
    },
    "dealer": {
      "buy": 37687157925,
      "sell": 57257089503,
      "net": -19569931578
    },
    "total_net": -55981788973
  },
  "20260519": {
    "date": "20260519",
    "foreign": {
      "buy": 407598284294,
      "sell": 470833237921,
      "net": -63234953627
    },
    "trust": {
      "buy": 43507183254,
      "sell": 35340610299,
      "net": 8166572955
    },
    "dealer": {
      "buy": 39303410899,
      "sell": 61654936331,
      "net": -22351525432
    },
    "total_net": -77419906104
  },
  "20260518": {
    "date": "20260518",
    "foreign": {
      "buy": 381235569281,
      "sell": 426476531903,
      "net": -45240962622
    },
    "trust": {
      "buy": 35500262069,
      "sell": 18835510074,
      "net": 16664751995
    },
    "dealer": {
      "buy": 42544938991,
      "sell": 56471324793,
      "net": -13926385802
    },
    "total_net": -42502596429
  },
  "20260515": {
    "date": "20260515",
    "foreign": {
      "buy": 486650810119,
      "sell": 497077396500,
      "net": -10426586381
    },
    "trust": {
      "buy": 34256621367,
      "sell": 35623859074,
      "net": -1367237707
    },
    "dealer": {
      "buy": 51391922860,
      "sell": 76335405886,
      "net": -24943483026
    },
    "total_net": -36737307114
  },
  "20260514": {
    "date": "20260514",
    "foreign": {
      "buy": 445429589660,
      "sell": 440886964957,
      "net": 4542624703
    },
    "trust": {
      "buy": 38968949177,
      "sell": 24672836385,
      "net": 14296112792
    },
    "dealer": {
      "buy": 46535060937,
      "sell": 47797790657,
      "net": -1262729720
    },
    "total_net": 17576007775
  },
  "20260513": {
    "date": "20260513",
    "foreign": {
      "buy": 429355353116,
      "sell": 472784827091,
      "net": -43429473975
    },
    "trust": {
      "buy": 51877210243,
      "sell": 25815578438,
      "net": 26061631805
    },
    "dealer": {
      "buy": 48875322871,
      "sell": 79141570130,
      "net": -30266247259
    },
    "total_net": -47634089429
  },
  "20260512": {
    "date": "20260512",
    "foreign": {
      "buy": 513039572893,
      "sell": 543533352834,
      "net": -30493779941
    },
    "trust": {
      "buy": 64219072068,
      "sell": 25902007032,
      "net": 38317065036
    },
    "dealer": {
      "buy": 62997592475,
      "sell": 83661174663,
      "net": -20663582188
    },
    "total_net": -12840297093
  },
  "20260511": {
    "date": "20260511",
    "foreign": {
      "buy": 428806127610,
      "sell": 439789631612,
      "net": -10983504002
    },
    "trust": {
      "buy": 29878651928,
      "sell": 17390367816,
      "net": 12488284112
    },
    "dealer": {
      "buy": 44725316406,
      "sell": 40995001609,
      "net": 3730314797
    },
    "total_net": 5235094907
  },
  "20260508": {
    "date": "20260508",
    "foreign": {
      "buy": 458232990582,
      "sell": 470317528153,
      "net": -12084537571
    },
    "trust": {
      "buy": 30337480232,
      "sell": 28218760625,
      "net": 2118719607
    },
    "dealer": {
      "buy": 54234190177,
      "sell": 64270919894,
      "net": -10036729717
    },
    "total_net": -20002547681
  },
  "20260507": {
    "date": "20260507",
    "foreign": {
      "buy": 481490560104,
      "sell": 435079033534,
      "net": 46411526570
    },
    "trust": {
      "buy": 34125520860,
      "sell": 19073192148,
      "net": 15052328712
    },
    "dealer": {
      "buy": 44556611432,
      "sell": 48698877879,
      "net": -4142266447
    },
    "total_net": 57321588835
  },
  "20260506": {
    "date": "20260506",
    "foreign": {
      "buy": 604269420170,
      "sell": 529164512376,
      "net": 75104907794
    },
    "trust": {
      "buy": 33542780925,
      "sell": 32021549000,
      "net": 1521231925
    },
    "dealer": {
      "buy": 65944682343,
      "sell": 75555292975,
      "net": -9610610632
    },
    "total_net": 67015529087
  },
  "20260505": {
    "date": "20260505",
    "foreign": {
      "buy": 358109943345,
      "sell": 354119676212,
      "net": 3990267133
    },
    "trust": {
      "buy": 26841381710,
      "sell": 23114456726,
      "net": 3726924984
    },
    "dealer": {
      "buy": 38588422748,
      "sell": 48675666564,
      "net": -10087243816
    },
    "total_net": -2370051699
  },
  "20260504": {
    "date": "20260504",
    "foreign": {
      "buy": 402015475312,
      "sell": 335039774559,
      "net": 66975700753
    },
    "trust": {
      "buy": 16194865482,
      "sell": 14166407936,
      "net": 2028457546
    },
    "dealer": {
      "buy": 48561133325,
      "sell": 39620532189,
      "net": 8940601136
    },
    "total_net": 77944759435
  }
}